LICENSE
MANIFEST.in
setup.py
docs/Makefile
docs/conf.py
docs/index.rst
docs/make.bat
gevent_socketio2.egg-info/PKG-INFO
gevent_socketio2.egg-info/SOURCES.txt
gevent_socketio2.egg-info/dependency_links.txt
gevent_socketio2.egg-info/requires.txt
gevent_socketio2.egg-info/top_level.txt
socketio/__init__.py
socketio/adapter.py
socketio/binary.py
socketio/client.py
socketio/debug_util.py
socketio/decorators.py
socketio/namespace.py
socketio/parser.py
socketio/sdjango.py
socketio/server.py
socketio/socket.py
socketio/engine/__init__.py
socketio/engine/handler.py
socketio/engine/parser.py
socketio/engine/response.py
socketio/engine/server.py
socketio/engine/socket.py
socketio/engine/transports.py
socketio/event_emitter/__init__.py
socketio/event_emitter/test.py
socketio/vender/__init__.py
socketio/vender/gunicorn.py