Metadata-Version: 1.0
Name: gevent-socketio2
Version: 0.2.8
Summary: A gevent implementation for socketio protocol 1.0
Home-page: https://github.com/shuoli84/gevent_socketio2
Author: Shuo Li
Author-email: shuoli84@gmail.com
License: MIT
Keywords: socketio,gevent,realtime
Platform: UNKNOWN
